setup.py
auditware/__init__.py
auditware/admin.py
auditware/apps.py
auditware/defaults.py
auditware/models.py
auditware/receivers.py
auditware/signals.py
auditware/utils.py
auditware/__pycache__/__init__.cpython-34.pyc
auditware/__pycache__/admin.cpython-34.pyc
auditware/__pycache__/apps.cpython-34.pyc
auditware/__pycache__/defaults.cpython-34.pyc
auditware/__pycache__/models.cpython-34.pyc
auditware/__pycache__/receivers.cpython-34.pyc
auditware/__pycache__/utils.cpython-34.pyc
auditware/middleware/__init__.py
auditware/middleware/logout.py
auditware/middleware/user.py
auditware/migrations/0001_initial.py
auditware/migrations/__init__.py
auditware/tests/__init__.py
auditware/tests/tests.py
auditware/tests/testsettings.py
auditware/tests/__pycache__/__init__.cpython-34.pyc
auditware/tests/__pycache__/testsettings.cpython-34.pyc
django_auditware.egg-info/PKG-INFO
django_auditware.egg-info/SOURCES.txt
django_auditware.egg-info/dependency_links.txt
django_auditware.egg-info/requires.txt
django_auditware.egg-info/top_level.txt